fpga/projects/04/debounce_filter.vhd
library IEEE;
use IEEE.std_logic_1164.all;
use IEEE.numeric_std.all;

entity Debounce_Filter is
  generic (DEBOUNCE_LIMIT : integer := 20);
  port (
   i_Clk        : in  std_logic;
   i_Bouncy     : in  std_logic;
   o_Debounced  : out std_logic
  );
end entity Debounce_Filter;

architecture rtl of Debounce_Filter is
  signal r_Count  : integer range 0 to DEBOUNCE_LIMIT := 0;
  signal r_State  : std_logic := '0';

begin
-- we make sure we wait some debounce limit time
-- T (ns/ms/..) = FPGA rate (Mhz/s) / DEBOUNCE_LIMIT
  process (i_Clk) is
  begin
    if rising_edge(i_Clk) then
      if (r_State /= i_Bouncy and r_Count < DEBOUNCE_LIMIT-1) then
        r_Count <= r_Count + 1;
      elsif r_Count = DEBOUNCE_LIMIT-1 then
        r_State <= i_Bouncy;
        r_Count <= 0;
      else
        r_Count <= 0;
      end if;
    end if;
  end process;

  o_Debounced <= r_State;
end architecture rtl;

fpga/projects/04/debounce_filter_tb_2.vhd
library IEEE;
use IEEE.std_logic_1164.all;
use IEEE.numeric_std.all;
use std.env.all;

entity Debounce_Filter_TB_2 is
-- Testbench doesn't have ports
end entity Debounce_Filter_TB_2;

architecture sim of Debounce_Filter_TB_2 is
  -- Test bench constants
  constant CLK_PERIOD : time := 10 ns;  -- 100MHz clock
  constant DEBOUNCE_LIMIT_TEST : integer := 5;  -- Smaller value for simulation
  
  -- Test bench signals
  signal tb_clk : std_logic := '0';
  signal tb_bouncy : std_logic := '0';
  signal tb_debounced : std_logic;
  signal tb_sim_done : boolean := false;

begin
  -- Instantiate the Unit Under Test (UUT)
  UUT: entity work.Debounce_Filter
    generic map (
      DEBOUNCE_LIMIT => DEBOUNCE_LIMIT_TEST
    )
    port map (
      i_Clk => tb_clk,
      i_Bouncy => tb_bouncy,
      o_Debounced => tb_debounced
    );

  -- Clock generation process
  p_clk: process
  begin
    while not tb_sim_done loop
      tb_clk <= '0';
      wait for CLK_PERIOD/2;
      tb_clk <= '1';
      wait for CLK_PERIOD/2;
    end loop;
    wait;
  end process p_clk;

  -- Stimulus process
  p_stim: process
  begin
    -- Initial state
    tb_bouncy <= '0';
    wait for CLK_PERIOD * 2;
    
    -- Test Case 1: Quick toggles (bouncing)
    report "Test Case 1: Quick toggles (bouncing)";
    tb_bouncy <= '1';
    wait for CLK_PERIOD * 2;
    tb_bouncy <= '0';
    wait for CLK_PERIOD * 1;
    tb_bouncy <= '1';
    wait for CLK_PERIOD * 1;
    tb_bouncy <= '0';
    wait for CLK_PERIOD * 2;
    
    -- Wait to see if output remains stable
    wait for CLK_PERIOD * (DEBOUNCE_LIMIT_TEST + 2);
    assert (tb_debounced = '0') severity failure;
    
    -- Test Case 2: Stable high input
    report "Test Case 2: Stable high input";
    tb_bouncy <= '1';
    wait for CLK_PERIOD * (DEBOUNCE_LIMIT_TEST + 5);
    assert (tb_debounced = '1') severity failure;
    
    -- Test Case 3: Stable low input
    report "Test Case 3: Stable low input";
    tb_bouncy <= '0';
    wait for CLK_PERIOD * (DEBOUNCE_LIMIT_TEST + 5);
    assert (tb_debounced = '0') severity failure;
    
    -- Test Case 4: Brief pulse shorter than debounce time
    report "Test Case 4: Brief pulse";
    tb_bouncy <= '1';
    wait for CLK_PERIOD * 2;
    tb_bouncy <= '0';
    wait for CLK_PERIOD * (DEBOUNCE_LIMIT_TEST + 2);
    assert (tb_debounced = '0') severity failure;

    -- Test Case 5: Debouncing from high to low
    report "Test Case 5: Brief high pulse";
    tb_bouncy <= '1';
    wait for CLK_PERIOD * (DEBOUNCE_LIMIT_TEST + 5);
    assert (tb_debounced = '1') severity failure;
    -- start bouncing
    tb_bouncy <= '0';
    wait for CLK_PERIOD;
    tb_bouncy <= '1';
    wait for CLK_PERIOD;
    tb_bouncy <= '0';
    wait for CLK_PERIOD * 4; -- not enough time for debouncing
    assert (tb_debounced = '1') severity failure;
    wait for CLK_PERIOD * 2;
    assert (tb_debounced = '0') severity failure;

    -- End simulation
    report "Simulation done!";
    tb_sim_done <= true;
    wait;
  end process p_stim;

  -- Monitor process to check outputs
  p_monitor: process
  begin
    wait for CLK_PERIOD;
    while not tb_sim_done loop
      if rising_edge(tb_clk) then
        report "Time: " & to_string(now) & 
               " Bouncy: " & std_logic'image(tb_bouncy) &
               " Debounced: " & std_logic'image(tb_debounced);
      end if;
      wait for CLK_PERIOD;
    end loop;
    wait;
  end process p_monitor;

end architecture sim;

fpga/projects/04/debounce_filter_wave_2.vcd
$date
  Sun Feb 23 20:05:29 2025
$end
$version
  GHDL v0
$end
$timescale
  1 fs
$end
$scope module standard $end
$upscope $end
$scope module textio $end
$upscope $end
$scope module std_logic_1164 $end
$upscope $end
$scope module numeric_std $end
$upscope $end
$scope module env $end
$upscope $end
$scope module debounce_filter_tb_2 $end
$var reg 1 ! tb_clk $end
$var reg 1 " tb_bouncy $end
$var reg 1 # tb_debounced $end
$var reg 1 $ tb_sim_done $end
$scope module uut $end
$var reg 1 % i_clk $end
$var reg 1 & i_bouncy $end
$var reg 1 ' o_debounced $end
$var integer 32 ( r_count $end
$var reg 1 ) r_state $end
$upscope $end
$upscope $end
$enddefinitions $end
#0
0!
0"
0#
0$
0%
0&
0'
b0 (
0)
#5000000
1!
1%
#10000000
0!
0%
#15000000
1!
1%
#20000000
0!
1"
0%
1&
#25000000
1!
1%
b1 (
#30000000
0!
0%
#35000000
1!
1%
b10 (
#40000000
0!
0"
0%
0&
#45000000
1!
1%
b0 (
#50000000
0!
1"
0%
1&
#55000000
1!
1%
b1 (
#60000000
0!
0"
0%
0&
#65000000
1!
1%
b0 (
#70000000
0!
0%
#75000000
1!
1%
#80000000
0!
0%
#85000000
1!
1%
#90000000
0!
0%
#95000000
1!
1%
#100000000
0!
0%
#105000000
1!
1%
#110000000
0!
0%
#115000000
1!
1%
#120000000
0!
0%
#125000000
1!
1%
#130000000
0!
0%
#135000000
1!
1%
#140000000
0!
0%
#145000000
1!
1%
#150000000
0!
1"
0%
1&
#155000000
1!
1%
b1 (
#160000000
0!
0%
#165000000
1!
1%
b10 (
#170000000
0!
0%
#175000000
1!
1%
b11 (
#180000000
0!
0%
#185000000
1!
1%
b100 (
#190000000
0!
0%
#195000000
1!
1#
1%
1'
b0 (
1)
#200000000
0!
0%
#205000000
1!
1%
#210000000
0!
0%
#215000000
1!
1%
#220000000
0!
0%
#225000000
1!
1%
#230000000
0!
0%
#235000000
1!
1%
#240000000
0!
0%
#245000000
1!
1%
#250000000
0!
0"
0%
0&
#255000000
1!
1%
b1 (
#260000000
0!
0%
#265000000
1!
1%
b10 (
#270000000
0!
0%
#275000000
1!
1%
b11 (
#280000000
0!
0%
#285000000
1!
1%
b100 (
#290000000
0!
0%
#295000000
1!
0#
1%
0'
b0 (
0)
#300000000
0!
0%
#305000000
1!
1%
#310000000
0!
0%
#315000000
1!
1%
#320000000
0!
0%
#325000000
1!
1%
#330000000
0!
0%
#335000000
1!
1%
#340000000
0!
0%
#345000000
1!
1%
#350000000
0!
1"
0%
1&
#355000000
1!
1%
b1 (
#360000000
0!
0%
#365000000
1!
1%
b10 (
#370000000
0!
0"
0%
0&
#375000000
1!
1%
b0 (
#380000000
0!
0%
#385000000
1!
1%
#390000000
0!
0%
#395000000
1!
1%
#400000000
0!
0%
#405000000
1!
1%
#410000000
0!
0%
#415000000
1!
1%
#420000000
0!
0%
#425000000
1!
1%
#430000000
0!
0%
#435000000
1!
1%
#440000000
0!
1$
0%
