fpga/projects/03/blink.vhd
-- Project #3: Blinking an LED
library ieee;
use ieee.std_logic_1164.all;

entity blink is
  port(
    i_clk     : in  std_logic;
    i_switch  : in  std_logic;
    o_led     : out std_logic
      );
end blink;

architecture rtl of blink is
  signal r_switch : std_logic := '0';
  signal r_led    : std_logic := '0';

begin
  process (i_clk) is
  begin
    if rising_edge(i_clk) then
      r_switch <= i_switch;
      if r_switch = '1' and i_switch = '0' then
        r_led <= not r_led;
      end if;
    end if;
  end process;

  o_led <= r_led;
end architecture rtl;

fpga/projects/03/blink_tb.vhd
library ieee;
use ieee.std_logic_1164.all;

entity blink_tb is
end blink_tb;

architecture behavior of blink_tb is
    -- Component Declaration
    component blink is
        port(
            i_clk    : in  std_logic;
            i_switch : in  std_logic;
            o_led    : out std_logic
        );
    end component;
    
    -- Constants
    constant CLK_PERIOD : time := 10 ns;
    
    -- Signals
    signal clk    : std_logic := '0';
    signal switch : std_logic := '0';
    signal led    : std_logic;
    
    -- Test completion signal
    signal sim_done : boolean := false;

begin
    -- Unit Under Test
    uut: blink port map (
        i_clk    => clk,
        i_switch => switch,
        o_led    => led
    );

    -- Clock generation process
    clk_gen: process
    begin
        while not sim_done loop
            clk <= '0';
            wait for CLK_PERIOD/2;
            clk <= '1';
            wait for CLK_PERIOD/2;
        end loop;
        wait;
    end process;

    -- Stimulus process
    stim_proc: process
    begin
        -- Initial state
        switch <= '0';
        wait for CLK_PERIOD * 2;
        
        -- Test Case 1: Single toggle
        -- Press switch
        switch <= '1';
        wait for CLK_PERIOD * 2;
        -- Release switch
        switch <= '0';
        wait for CLK_PERIOD * 2;
        -- LED should be '1'
        assert led = '1'
            report "Test Case 1 Failed: LED should be ON after first toggle"
            severity error;
            
        -- Test Case 2: Second toggle
        -- Press switch
        switch <= '1';
        wait for CLK_PERIOD * 2;
        -- Release switch
        switch <= '0';
        wait for CLK_PERIOD * 2;
        -- LED should be '0'
        assert led = '0'
            report "Test Case 2 Failed: LED should be OFF after second toggle"
            severity error;
            
        -- Test Case 3: Quick press (glitch test)
        switch <= '1';
        wait for CLK_PERIOD/2;  -- Quick press shorter than clock period
        switch <= '0';
        wait for CLK_PERIOD * 2;
        -- LED state should not change due to synchronous design
        assert led = '0'
            report "Test Case 3 Failed: LED should not toggle on glitch"
            severity error;
            
        -- Test Case 4: Multiple clock cycles high
        switch <= '1';
        wait for CLK_PERIOD * 5;  -- Hold switch high for multiple cycles
        switch <= '0';
        wait for CLK_PERIOD * 2;
        -- LED should toggle only once
        assert led = '1'
            report "Test Case 4 Failed: LED should toggle only once on release"
            severity error;

        -- End simulation
        report "Simulation completed successfully";
        sim_done <= true;
        wait;
    end process;

end behavior;

fpga/projects/03/blink_tb_wave.vcd
$date
  Thu Feb 20 14:49:20 2025
$end
$version
  GHDL v0
$end
$timescale
  1 fs
$end
$scope module standard $end
$upscope $end
$scope module std_logic_1164 $end
$upscope $end
$scope module blink_tb $end
$var reg 1 ! clk $end
$var reg 1 " switch $end
$var reg 1 # led $end
$var reg 1 $ sim_done $end
$scope module uut $end
$var reg 1 % i_clk $end
$var reg 1 & i_switch $end
$var reg 1 ' o_led $end
$var reg 1 ( r_switch $end
$var reg 1 ) r_led $end
$upscope $end
$upscope $end
$enddefinitions $end
#0
0!
0"
0#
0$
0%
0&
0'
0(
0)
#5000000
1!
1%
#10000000
0!
0%
#15000000
1!
1%
#20000000
0!
1"
0%
1&
#25000000
1!
1%
1(
#30000000
0!
0%
#35000000
1!
1%
#40000000
0!
0"
0%
0&
#45000000
1!
1#
1%
1'
0(
1)
#50000000
0!
0%
#55000000
1!
1%
#60000000
0!
1"
0%
1&
#65000000
1!
1%
1(
#70000000
0!
0%
#75000000
1!
1%
#80000000
0!
0"
0%
0&
#85000000
1!
0#
1%
0'
0(
0)
#90000000
0!
0%
#95000000
1!
1%
#100000000
0!
1"
0%
1&
#105000000
1!
0"
1%
0&
#110000000
0!
0%
#115000000
1!
1%
#120000000
0!
0%
#125000000
1!
1"
1%
1&
1(
#130000000
0!
0%
#135000000
1!
1%
#140000000
0!
0%
#145000000
1!
1%
#150000000
0!
0%
#155000000
1!
1%
#160000000
0!
0%
#165000000
1!
1%
#170000000
0!
0%
#175000000
1!
0"
1#
1%
0&
1'
0(
1)
#180000000
0!
0%
#185000000
1!
1%
#190000000
0!
0%
#195000000
1!
1$
1%
